MANIFEST.in
README.rst
setup.py
pydivide/__init__.py
pydivide/access.txt
pydivide/altplot.py
pydivide/bin.py
pydivide/cleanup_files.py
pydivide/compare_versions.py
pydivide/corona.py
pydivide/create_model_maps.py
pydivide/download_files.py
pydivide/download_files_utilities.py
pydivide/fullplot.py
pydivide/insitu_search.py
pydivide/interpol_model.py
pydivide/map2d.py
pydivide/occultation.py
pydivide/periapse.py
pydivide/plot.py
pydivide/read.py
pydivide/read_model_results.py
pydivide/resample.py
pydivide/standards.py
pydivide/tplot_varcreate.py
pydivide/utilities.py
pydivide/version.txt
pydivide.egg-info/PKG-INFO
pydivide.egg-info/SOURCES.txt
pydivide.egg-info/dependency_links.txt
pydivide.egg-info/not-zip-safe
pydivide.egg-info/requires.txt
pydivide.egg-info/top_level.txt
pydivide/basemaps/MAG_Connerny_2005.jpg
pydivide/basemaps/MDIM_2500x1250.jpg
pydivide/basemaps/MOLA_BW_2500x1250.jpg
pydivide/basemaps/MOLA_color_2500x1250.jpg
pydivide/basemaps/MarsElevation_2500x1250.jpg
pydivide/orbitfiles/orbits.txt