Metadata-Version: 1.0
Name: pydivide
Version: 0.2.16
Summary: A tool to plot MAVEN data
Home-page: http://github.com/MAVENSDC/pydivide
Author: MAVEN SDC
Author-email: mavensdc@lasp.colorado.edu
License: MIT
Keywords: tplot maven mars lasp idl divide spedas
Platform: UNKNOWN
